nodeprocess/__init__.py
nodeprocess/nodeprocess.py
nodeprocess-0.0.2.dist-info/METADATA
nodeprocess-0.0.2.dist-info/WHEEL
nodeprocess-0.0.2.dist-info/top_level.txt
nodeprocess-0.0.2.dist-info/RECORD
